{
  "configurations": [
    {
      "name": "Win32-Debug-Full-Demo",
      "generator": "Ninja",
      "configurationType": "Debug",
      "buildRoot": "${projectDir}\\build\\${name}",
      "installRoot": "${projectDir}\\build\\bin\\${name}",
      "cmakeCommandArgs": "",
      "buildCommandArgs": "",
      "ctestCommandArgs": "",
      "inheritEnvironments": [ "msvc_x86" ],
      "variables": [
        {
          "name": "BLINKY_DEMO",
          "value": "False",
          "type": "BOOL"
        },
        {
          "name": "BOOST_INCLUDEDIR",
          "value": "D:/development/libraries/boost/x86/boost_1_77_0",
          "type": "STRING"
        },
        {
          "name": "BOOST_LIBRARYDIR",
          "value": "D:/development/libraries/boost/x86/boost_1_77_0/lib32-msvc-14.2",
          "type": "STRING"
        },
        {
          "name": "BOOST_ROOT",
          "value": "D:/development/libraries/boost/x86/boost_1_77_0",
          "type": "STRING"
        }
      ]
    },
    {
      "name": "Win32-Debug-Blinky-Demo",
      "generator": "Ninja",
      "configurationType": "Debug",
      "buildRoot": "${projectDir}\\build\\${name}",
      "installRoot": "${projectDir}\\build\\bin\\${name}",
      "cmakeCommandArgs": "",
      "buildCommandArgs": "",
      "ctestCommandArgs": "",
      "inheritEnvironments": [ "msvc_x86" ]
    },
    {
      "name": "Win32-Debug-Simulator-All-Tasks",
      "generator": "Ninja",
      "configurationType": "Debug",
      "buildRoot": "${projectDir}\\build\\${name}",
      "installRoot": "${projectDir}\\build\\bin\\${name}",
      "cmakeCommandArgs": "",
      "buildCommandArgs": "",
      "ctestCommandArgs": "",
      "inheritEnvironments": [ "msvc_x86" ],
      "variables": [
        {
          "name": "TASK_CHECK",
          "value": "True",
          "type": "BOOL"
        },
        {
          "name": "BOOST_ROOT",
          "value": "D:/development/libraries/boost/x86/boost_1_77_0",
          "type": "STRING"
        },
        {
          "name": "BOOST_LIBRARYDIR",
          "value": "D:/development/libraries/boost/x86/boost_1_77_0/lib32-msvc-14.2",
          "type": "STRING"
        },
        {
          "name": "BOOST_INCLUDEDIR",
          "value": "D:/development/libraries/boost/x86/boost_1_77_0",
          "type": "STRING"
        }
      ]
    },
    {
      "name": "Win32-Debug-Simulator-Check-Task-Only",
      "generator": "Ninja",
      "configurationType": "Debug",
      "buildRoot": "${projectDir}\\build\\${name}",
      "installRoot": "${projectDir}\\build\\bin\\${name}",
      "cmakeCommandArgs": "",
      "buildCommandArgs": "",
      "ctestCommandArgs": "",
      "inheritEnvironments": [ "msvc_x86" ],
      "variables": [
        {
          "name": "TASK_CHECK",
          "value": "true",
          "type": "BOOL"
        },
        {
          "name": "TASK_BLOCK_TIM",
          "value": "false",
          "type": "BOOL"
        },
        {
          "name": "TASK_INDEF_DELAY_NOTIF",
          "value": "False",
          "type": "BOOL"
        },
        {
          "name": "TIMER_PERIODIC_ISR_TESTS",
          "value": "False",
          "type": "BOOL"
        },
        {
          "name": "TEST_DELETE_MUTEX",
          "value": "False",
          "type": "BOOL"
        },
        {
          "name": "TASK_TIMER_QUERY",
          "value": "False",
          "type": "BOOL"
        },
        {
          "name": "TASK_TIMER",
          "value": "False",
          "type": "BOOL"
        },
        {
          "name": "QUEUE_SET_ACCESS_ISR",
          "value": "False",
          "type": "BOOL"
        },
        {
          "name": "EVENT_GROUP_ISR",
          "value": "False",
          "type": "BOOL"
        },
        {
          "name": "NOTIFY_TASK_ISR",
          "value": "False",
          "type": "BOOL"
        },
        {
          "name": "QUEUE_OVERWRITE_PERIODIC_ISR",
          "value": "False",
          "type": "BOOL"
        },
        {
          "name": "QUEUE_SET_ACCESS_POLL_ISR",
          "value": "False",
          "type": "BOOL"
        },
        {
          "name": "SEM_TEST_ISR",
          "value": "False",
          "type": "BOOL"
        },
        {
          "name": "STREAM_BUFFER_PROC",
          "value": "False",
          "type": "BOOL"
        },
        {
          "name": "STREAM_BUFFER_SEND_ISR",
          "value": "False",
          "type": "BOOL"
        },
        {
          "name": "TASK_ABORT_DELAY",
          "value": "False",
          "type": "BOOL"
        },
        {
          "name": "TASK_BLOCKING_QUEUE",
          "value": "False",
          "type": "BOOL"
        },
        {
          "name": "TASK_DEATH",
          "value": "False",
          "type": "BOOL"
        },
        {
          "name": "TASK_COUNT_SEM",
          "value": "False",
          "type": "BOOL"
        },
        {
          "name": "TASK_EVENT_GROUPS",
          "value": "False",
          "type": "BOOL"
        },
        {
          "name": "TASK_DYNAMIC_PRIOR",
          "value": "False",
          "type": "BOOL"
        },
        {
          "name": "TASK_FLOP",
          "value": "False",
          "type": "BOOL"
        },
        {
          "name": "TASK_GEN_QUEUE",
          "value": "False",
          "type": "BOOL"
        },
        {
          "name": "TASK_INDEF_DELAY_SEM",
          "value": "False",
          "type": "BOOL"
        },
        {
          "name": "TASK_INT_SEM_TEST",
          "value": "False",
          "type": "BOOL"
        },
        {
          "name": "TASK_INTEGER",
          "value": "False",
          "type": "BOOL"
        },
        {
          "name": "TASK_MESSAGE_BUFF_AMP",
          "value": "False",
          "type": "BOOL"
        },
        {
          "name": "TASK_MESSAGE_BUFFER",
          "value": "False",
          "type": "BOOL"
        },
        {
          "name": "TASK_PEEK_QUEUE",
          "value": "False",
          "type": "BOOL"
        },
        {
          "name": "TASK_PEND_FUNC_CALL",
          "value": "False",
          "type": "BOOL"
        },
        {
          "name": "TASK_POLL_QUEUE",
          "value": "False",
          "type": "BOOL"
        },
        {
          "name": "TASK_QUEUE_OVERWRITE",
          "value": "False",
          "type": "BOOL"
        },
        {
          "name": "TASK_QUEUE_SET_POLL",
          "value": "False",
          "type": "BOOL"
        },
        {
          "name": "TASK_QUEUE_SET",
          "value": "False",
          "type": "BOOL"
        },
        {
          "name": "TASK_QUEUE_SPACE_AVAIL",
          "value": "False",
          "type": "BOOL"
        },
        {
          "name": "TASK_REC_MUTEX",
          "value": "False",
          "type": "BOOL"
        },
        {
          "name": "TASK_SEM_TEST",
          "value": "False",
          "type": "BOOL"
        },
        {
          "name": "TASK_STATIC_ALLOC",
          "value": "False",
          "type": "BOOL"
        },
        {
          "name": "TASK_STREAM_BUFF_INT",
          "value": "False",
          "type": "BOOL"
        },
        {
          "name": "TASK_STREAM_BUFFER",
          "value": "False",
          "type": "BOOL"
        },
        {
          "name": "TASK_TASK_INTERNAL",
          "value": "False",
          "type": "BOOL"
        },
        {
          "name": "TASK_TASK_NOTIFY",
          "value": "False",
          "type": "BOOL"
        }
      ]
    },
    {
      "name": "Win32-Debug-Simulator-Conf1",
      "generator": "Ninja",
      "configurationType": "Debug",
      "buildRoot": "${projectDir}\\build\\${name}",
      "installRoot": "${projectDir}\\build\\bin\\${name}",
      "cmakeCommandArgs": "",
      "buildCommandArgs": "",
      "ctestCommandArgs": "",
      "inheritEnvironments": [ "msvc_x86" ],
      "variables": [
        {
          "name": "TASK_CHECK",
          "value": "true",
          "type": "BOOL"
        },
        {
          "name": "TASK_BLOCK_TIM",
          "value": "false",
          "type": "BOOL"
        },
        {
          "name": "TASK_INDEF_DELAY_NOTIF",
          "value": "False",
          "type": "BOOL"
        },
        {
          "name": "TIMER_PERIODIC_ISR_TESTS",
          "value": "False",
          "type": "BOOL"
        },
        {
          "name": "TEST_DELETE_MUTEX",
          "value": "False",
          "type": "BOOL"
        },
        {
          "name": "TASK_TIMER_QUERY",
          "value": "False",
          "type": "BOOL"
        },
        {
          "name": "TASK_TIMER",
          "value": "False",
          "type": "BOOL"
        },
        {
          "name": "QUEUE_SET_ACCESS_ISR",
          "value": "False",
          "type": "BOOL"
        },
        {
          "name": "EVENT_GROUP_ISR",
          "value": "False",
          "type": "BOOL"
        },
        {
          "name": "NOTIFY_TASK_ISR",
          "value": "False",
          "type": "BOOL"
        },
        {
          "name": "QUEUE_OVERWRITE_PERIODIC_ISR",
          "value": "False",
          "type": "BOOL"
        },
        {
          "name": "QUEUE_SET_ACCESS_POLL_ISR",
          "value": "False",
          "type": "BOOL"
        },
        {
          "name": "SEM_TEST_ISR",
          "value": "False",
          "type": "BOOL"
        },
        {
          "name": "STREAM_BUFFER_PROC",
          "value": "False",
          "type": "BOOL"
        },
        {
          "name": "STREAM_BUFFER_SEND_ISR",
          "value": "False",
          "type": "BOOL"
        },
        {
          "name": "TASK_ABORT_DELAY",
          "value": "False",
          "type": "BOOL"
        },
        {
          "name": "TASK_BLOCKING_QUEUE",
          "value": "False",
          "type": "BOOL"
        },
        {
          "name": "TASK_DEATH",
          "value": "False",
          "type": "BOOL"
        },
        {
          "name": "TASK_COUNT_SEM",
          "value": "False",
          "type": "BOOL"
        },
        {
          "name": "TASK_EVENT_GROUPS",
          "value": "False",
          "type": "BOOL"
        },
        {
          "name": "TASK_DYNAMIC_PRIOR",
          "value": "False",
          "type": "BOOL"
        },
        {
          "name": "TASK_FLOP",
          "value": "False",
          "type": "BOOL"
        },
        {
          "name": "TASK_GEN_QUEUE",
          "value": "False",
          "type": "BOOL"
        },
        {
          "name": "TASK_INDEF_DELAY_SEM",
          "value": "False",
          "type": "BOOL"
        },
        {
          "name": "TASK_INT_SEM_TEST",
          "value": "False",
          "type": "BOOL"
        },
        {
          "name": "TASK_INTEGER",
          "value": "False",
          "type": "BOOL"
        },
        {
          "name": "TASK_MESSAGE_BUFF_AMP",
          "value": "False",
          "type": "BOOL"
        },
        {
          "name": "TASK_MESSAGE_BUFFER",
          "value": "False",
          "type": "BOOL"
        },
        {
          "name": "TASK_PEEK_QUEUE",
          "value": "False",
          "type": "BOOL"
        },
        {
          "name": "TASK_PEND_FUNC_CALL",
          "value": "False",
          "type": "BOOL"
        },
        {
          "name": "TASK_POLL_QUEUE",
          "value": "True",
          "type": "BOOL"
        },
        {
          "name": "TASK_QUEUE_OVERWRITE",
          "value": "False",
          "type": "BOOL"
        },
        {
          "name": "TASK_QUEUE_SET_POLL",
          "value": "False",
          "type": "BOOL"
        },
        {
          "name": "TASK_QUEUE_SET",
          "value": "False",
          "type": "BOOL"
        },
        {
          "name": "TASK_QUEUE_SPACE_AVAIL",
          "value": "False",
          "type": "BOOL"
        },
        {
          "name": "TASK_REC_MUTEX",
          "value": "False",
          "type": "BOOL"
        },
        {
          "name": "TASK_SEM_TEST",
          "value": "False",
          "type": "BOOL"
        },
        {
          "name": "TASK_STATIC_ALLOC",
          "value": "False",
          "type": "BOOL"
        },
        {
          "name": "TASK_STREAM_BUFF_INT",
          "value": "False",
          "type": "BOOL"
        },
        {
          "name": "TASK_STREAM_BUFFER",
          "value": "False",
          "type": "BOOL"
        },
        {
          "name": "TASK_TASK_INTERNAL",
          "value": "False",
          "type": "BOOL"
        },
        {
          "name": "TASK_TASK_NOTIFY",
          "value": "False",
          "type": "BOOL"
        },
        {
          "name": "BOOST_ROOT",
          "value": "D:/development/libraries/boost/x86/boost_1_77_0",
          "type": "STRING"
        },
        {
          "name": "BOOST_INCLUDEDIR",
          "value": "D:/development/libraries/boost/x86/boost_1_77_0",
          "type": "STRING"
        },
        {
          "name": "BOOST_LIBRARYDIR",
          "value": "D:/development/libraries/boost/x86/boost_1_77_0/lib32-msvc-14.2",
          "type": "STRING"
        },
        {
          "name": "TASK_TASK_NOTIFY_ARRAY",
          "value": "False",
          "type": "BOOL"
        },
        {
          "name": "USER_DEBUG",
          "value": "False",
          "type": "BOOL"
        }
      ]
    },
    {
      "name": "Win32-Debug-FaultInjector",
      "generator": "Ninja",
      "configurationType": "Debug",
      "buildRoot": "${projectDir}\\build\\${name}",
      "installRoot": "${projectDir}\\build\\bin\\${name}",
      "cmakeCommandArgs": "",
      "buildCommandArgs": "",
      "ctestCommandArgs": "",
      "inheritEnvironments": [ "msvc_x86" ],
      "variables": [
        {
          "name": "TASK_CHECK",
          "value": "true",
          "type": "BOOL"
        },
        {
          "name": "TASK_BLOCK_TIM",
          "value": "false",
          "type": "BOOL"
        },
        {
          "name": "TASK_INDEF_DELAY_NOTIF",
          "value": "False",
          "type": "BOOL"
        },
        {
          "name": "TIMER_PERIODIC_ISR_TESTS",
          "value": "False",
          "type": "BOOL"
        },
        {
          "name": "TEST_DELETE_MUTEX",
          "value": "False",
          "type": "BOOL"
        },
        {
          "name": "TASK_TIMER_QUERY",
          "value": "False",
          "type": "BOOL"
        },
        {
          "name": "TASK_TIMER",
          "value": "False",
          "type": "BOOL"
        },
        {
          "name": "QUEUE_SET_ACCESS_ISR",
          "value": "False",
          "type": "BOOL"
        },
        {
          "name": "EVENT_GROUP_ISR",
          "value": "False",
          "type": "BOOL"
        },
        {
          "name": "NOTIFY_TASK_ISR",
          "value": "False",
          "type": "BOOL"
        },
        {
          "name": "QUEUE_OVERWRITE_PERIODIC_ISR",
          "value": "False",
          "type": "BOOL"
        },
        {
          "name": "QUEUE_SET_ACCESS_POLL_ISR",
          "value": "False",
          "type": "BOOL"
        },
        {
          "name": "SEM_TEST_ISR",
          "value": "False",
          "type": "BOOL"
        },
        {
          "name": "STREAM_BUFFER_PROC",
          "value": "False",
          "type": "BOOL"
        },
        {
          "name": "STREAM_BUFFER_SEND_ISR",
          "value": "False",
          "type": "BOOL"
        },
        {
          "name": "TASK_ABORT_DELAY",
          "value": "False",
          "type": "BOOL"
        },
        {
          "name": "TASK_BLOCKING_QUEUE",
          "value": "False",
          "type": "BOOL"
        },
        {
          "name": "TASK_DEATH",
          "value": "False",
          "type": "BOOL"
        },
        {
          "name": "TASK_COUNT_SEM",
          "value": "False",
          "type": "BOOL"
        },
        {
          "name": "TASK_EVENT_GROUPS",
          "value": "False",
          "type": "BOOL"
        },
        {
          "name": "TASK_DYNAMIC_PRIOR",
          "value": "False",
          "type": "BOOL"
        },
        {
          "name": "TASK_FLOP",
          "value": "False",
          "type": "BOOL"
        },
        {
          "name": "TASK_GEN_QUEUE",
          "value": "False",
          "type": "BOOL"
        },
        {
          "name": "TASK_INDEF_DELAY_SEM",
          "value": "False",
          "type": "BOOL"
        },
        {
          "name": "TASK_INT_SEM_TEST",
          "value": "False",
          "type": "BOOL"
        },
        {
          "name": "TASK_INTEGER",
          "value": "False",
          "type": "BOOL"
        },
        {
          "name": "TASK_MESSAGE_BUFF_AMP",
          "value": "False",
          "type": "BOOL"
        },
        {
          "name": "TASK_MESSAGE_BUFFER",
          "value": "True",
          "type": "BOOL"
        },
        {
          "name": "TASK_PEEK_QUEUE",
          "value": "False",
          "type": "BOOL"
        },
        {
          "name": "TASK_PEND_FUNC_CALL",
          "value": "False",
          "type": "BOOL"
        },
        {
          "name": "TASK_POLL_QUEUE",
          "value": "False",
          "type": "BOOL"
        },
        {
          "name": "TASK_QUEUE_OVERWRITE",
          "value": "False",
          "type": "BOOL"
        },
        {
          "name": "TASK_QUEUE_SET_POLL",
          "value": "False",
          "type": "BOOL"
        },
        {
          "name": "TASK_QUEUE_SET",
          "value": "False",
          "type": "BOOL"
        },
        {
          "name": "TASK_QUEUE_SPACE_AVAIL",
          "value": "False",
          "type": "BOOL"
        },
        {
          "name": "TASK_REC_MUTEX",
          "value": "False",
          "type": "BOOL"
        },
        {
          "name": "TASK_SEM_TEST",
          "value": "False",
          "type": "BOOL"
        },
        {
          "name": "TASK_STATIC_ALLOC",
          "value": "False",
          "type": "BOOL"
        },
        {
          "name": "TASK_STREAM_BUFF_INT",
          "value": "False",
          "type": "BOOL"
        },
        {
          "name": "TASK_STREAM_BUFFER",
          "value": "False",
          "type": "BOOL"
        },
        {
          "name": "TASK_TASK_INTERNAL",
          "value": "False",
          "type": "BOOL"
        },
        {
          "name": "TASK_TASK_NOTIFY",
          "value": "False",
          "type": "BOOL"
        },
        {
          "name": "BOOST_ROOT",
          "value": "D:/development/libraries/boost/x86/boost_1_77_0",
          "type": "STRING"
        },
        {
          "name": "BOOST_INCLUDEDIR",
          "value": "D:/development/libraries/boost/x86/boost_1_77_0",
          "type": "STRING"
        },
        {
          "name": "BOOST_LIBRARYDIR",
          "value": "D:/development/libraries/boost/x86/boost_1_77_0/lib32-msvc-14.2",
          "type": "STRING"
        },
        {
          "name": "TASK_TASK_NOTIFY_ARRAY",
          "value": "False",
          "type": "BOOL"
        },
        {
          "name": "USER_DEBUG",
          "value": "False",
          "type": "BOOL"
        }
      ]
    }
  ]
}